Metadata-Version: 2.1
Name: random-otp
Version: 1.0.0
Summary: A Python package for generating random OTPs
Home-page: UNKNOWN
Author: Abhijith
Author-email: abhis@tuta.io
License: UNKNOWN
Platform: UNKNOWN
Classifier: Programming Language :: Python :: 3
Classifier: License :: OSI Approved :: MIT License
Classifier: Operating System :: OS Independent
